yatage/__init__.py
yatage/__version__.py
yatage/cli.py
yatage/commands.py
yatage/exceptions.py
yatage/game.py
yatage/inventory.py
yatage/item.py
yatage/loop.py
yatage/room.py
yatage/utils.py
yatage/world.py
yatage-1.0.0b2.dist-info/LICENSE.md
yatage-1.0.0b2.dist-info/METADATA
yatage-1.0.0b2.dist-info/WHEEL
yatage-1.0.0b2.dist-info/entry_points.txt
yatage-1.0.0b2.dist-info/top_level.txt
yatage-1.0.0b2.dist-info/RECORD
