Metadata-Version: 2.1
Name: yatage
Version: 1.0.0b2
Summary: Yet Another Text Adventure Game Engine
Home-page: https://github.com/EpocDotFr/yatage
Author: Maxime "Epoc" G.
Author-email: contact.nospam@epoc.nospam.fr
License: DBAD
Project-URL: Documentation, https://epocdotfr.github.io/yatage/
Project-URL: Source, https://github.com/EpocDotFr/yatage
Project-URL: Tracker, https://github.com/EpocDotFr/yatage/issues
Platform: UNKNOWN
Classifier: Development Status :: 4 - Beta
Classifier: Environment :: Console
Classifier: Operating System :: OS Independent
Classifier: Programming Language :: Python
Classifier: Programming Language :: Python :: 3.8
Classifier: Programming Language :: Python :: 3.9
Classifier: Programming Language :: Python :: 3.10
Classifier: Programming Language :: Python :: 3.11
Classifier: Topic :: Games/Entertainment
Requires-Python: >=3.8
Requires-Dist: pyyaml (~=6.0)
Provides-Extra: dev
Requires-Dist: Sphinx (~=5.3) ; extra == 'dev'
Requires-Dist: pytest (~=7.2) ; extra == 'dev'
Requires-Dist: twine (~=4.0) ; extra == 'dev'
Requires-Dist: wheel (~=0.38) ; extra == 'dev'
